<?xml version="1.0" encoding="UTF-8"?>
<config xmlns="http://www.knime.org/2008/09/XMLConfig" xmlns:xsi="http://www.w3.org/2001/XMLSchema-instance" xsi:schemaLocation="http://www.knime.org/2008/09/XMLConfig http://www.knime.org/XMLConfig_2008_09.xsd" key="spec.xml">
<entry key="spec_name" type="xstring" value="default"/>
<entry key="number_columns" type="xint" value="16"/>
<config key="column_spec_0">
<entry key="column_name" type="xstring" value="id"/>
<config key="element_names">
<entry key="array-size" type="xint" value="0"/>
</config>
<config key="column_type">
<entry key="cell_class" type="xstring" value="org.knime.core.data.def.DoubleCell"/>
</config>
<config key="column_domain">
<config key="lower_bound">
<entry key="datacell" type="xstring" value="org.knime.core.data.def.DoubleCell"/>
<config key="org.knime.core.data.def.DoubleCell">
<entry key="DoubleCell" type="xdouble" value="3.06667535E8"/>
</config>
</config>
<config key="upper_bound">
<entry key="datacell" type="xstring" value="org.knime.core.data.def.DoubleCell"/>
<config key="org.knime.core.data.def.DoubleCell">
<entry key="DoubleCell" type="xdouble" value="2.3300580095E10"/>
</config>
</config>
</config>
<config key="column_properties"/>
<config key="meta_data"/>
</config>
<config key="column_spec_1">
<entry key="column_name" type="xstring" value="user"/>
<config key="element_names">
<entry key="array-size" type="xint" value="0"/>
</config>
<config key="column_type">
<entry key="cell_class" type="xstring" value="org.knime.core.data.def.StringCell"/>
</config>
<config key="column_domain">
<config key="possible_values">
<entry key="array-size" type="xint" value="15"/>
<config key="0">
<entry key="datacell" type="xstring" value="org.knime.core.data.def.StringCell"/>
<config key="org.knime.core.data.def.StringCell">
<entry key="StringCell" type="xstring" value="13818951@N08"/>
</config>
</config>
<config key="1">
<entry key="datacell" type="xstring" value="org.knime.core.data.def.StringCell"/>
<config key="org.knime.core.data.def.StringCell">
<entry key="StringCell" type="xstring" value="49948988@N03"/>
</config>
</config>
<config key="2">
<entry key="datacell" type="xstring" value="org.knime.core.data.def.StringCell"/>
<config key="org.knime.core.data.def.StringCell">
<entry key="StringCell" type="xstring" value="60447100@N04"/>
</config>
</config>
<config key="3">
<entry key="datacell" type="xstring" value="org.knime.core.data.def.StringCell"/>
<config key="org.knime.core.data.def.StringCell">
<entry key="StringCell" type="xstring" value="54979873@N08"/>
</config>
</config>
<config key="4">
<entry key="datacell" type="xstring" value="org.knime.core.data.def.StringCell"/>
<config key="org.knime.core.data.def.StringCell">
<entry key="StringCell" type="xstring" value="58001955@N03"/>
</config>
</config>
<config key="5">
<entry key="datacell" type="xstring" value="org.knime.core.data.def.StringCell"/>
<config key="org.knime.core.data.def.StringCell">
<entry key="StringCell" type="xstring" value="19710808@N05"/>
</config>
</config>
<config key="6">
<entry key="datacell" type="xstring" value="org.knime.core.data.def.StringCell"/>
<config key="org.knime.core.data.def.StringCell">
<entry key="StringCell" type="xstring" value="77161041@N00"/>
</config>
</config>
<config key="7">
<entry key="datacell" type="xstring" value="org.knime.core.data.def.StringCell"/>
<config key="org.knime.core.data.def.StringCell">
<entry key="StringCell" type="xstring" value="83294602@N03"/>
</config>
</config>
<config key="8">
<entry key="datacell" type="xstring" value="org.knime.core.data.def.StringCell"/>
<config key="org.knime.core.data.def.StringCell">
<entry key="StringCell" type="xstring" value="54458745@N04"/>
</config>
</config>
<config key="9">
<entry key="datacell" type="xstring" value="org.knime.core.data.def.StringCell"/>
<config key="org.knime.core.data.def.StringCell">
<entry key="StringCell" type="xstring" value="135974300@N02"/>
</config>
</config>
<config key="10">
<entry key="datacell" type="xstring" value="org.knime.core.data.def.StringCell"/>
<config key="org.knime.core.data.def.StringCell">
<entry key="StringCell" type="xstring" value="75906220@N07"/>
</config>
</config>
<config key="11">
<entry key="datacell" type="xstring" value="org.knime.core.data.def.StringCell"/>
<config key="org.knime.core.data.def.StringCell">
<entry key="StringCell" type="xstring" value="46032524@N00"/>
</config>
</config>
<config key="12">
<entry key="datacell" type="xstring" value="org.knime.core.data.def.StringCell"/>
<config key="org.knime.core.data.def.StringCell">
<entry key="StringCell" type="xstring" value="20342758@N00"/>
</config>
</config>
<config key="13">
<entry key="datacell" type="xstring" value="org.knime.core.data.def.StringCell"/>
<config key="org.knime.core.data.def.StringCell">
<entry key="StringCell" type="xstring" value="39685874@N00"/>
</config>
</config>
<config key="14">
<entry key="datacell" type="xstring" value="org.knime.core.data.def.StringCell"/>
<config key="org.knime.core.data.def.StringCell">
<entry key="StringCell" type="xstring" value="52382736@N00"/>
</config>
</config>
</config>
</config>
<config key="column_properties"/>
<config key="meta_data"/>
</config>
<config key="column_spec_2">
<entry key="column_name" type="xstring" value="lat"/>
<config key="element_names">
<entry key="array-size" type="xint" value="0"/>
</config>
<config key="column_type">
<entry key="cell_class" type="xstring" value="org.knime.core.data.def.DoubleCell"/>
</config>
<config key="column_domain">
<config key="lower_bound">
<entry key="datacell" type="xstring" value="org.knime.core.data.def.DoubleCell"/>
<config key="org.knime.core.data.def.DoubleCell">
<entry key="DoubleCell" type="xdouble" value="45.475833"/>
</config>
</config>
<config key="upper_bound">
<entry key="datacell" type="xstring" value="org.knime.core.data.def.DoubleCell"/>
<config key="org.knime.core.data.def.DoubleCell">
<entry key="DoubleCell" type="xdouble" value="46.040333"/>
</config>
</config>
</config>
<config key="column_properties"/>
<config key="meta_data"/>
</config>
<config key="column_spec_3">
<entry key="column_name" type="xstring" value="long"/>
<config key="element_names">
<entry key="array-size" type="xint" value="0"/>
</config>
<config key="column_type">
<entry key="cell_class" type="xstring" value="org.knime.core.data.def.DoubleCell"/>
</config>
<config key="column_domain">
<config key="lower_bound">
<entry key="datacell" type="xstring" value="org.knime.core.data.def.DoubleCell"/>
<config key="org.knime.core.data.def.DoubleCell">
<entry key="DoubleCell" type="xdouble" value="4.442983"/>
</config>
</config>
<config key="upper_bound">
<entry key="datacell" type="xstring" value="org.knime.core.data.def.DoubleCell"/>
<config key="org.knime.core.data.def.DoubleCell">
<entry key="DoubleCell" type="xdouble" value="5.21667"/>
</config>
</config>
</config>
<config key="column_properties"/>
<config key="meta_data"/>
</config>
<config key="column_spec_4">
<entry key="column_name" type="xstring" value="tags"/>
<config key="element_names">
<entry key="array-size" type="xint" value="0"/>
</config>
<config key="column_type">
<entry key="cell_class" type="xstring" value="org.knime.core.data.def.StringCell"/>
</config>
<config key="column_domain">
<config key="possible_values">
<entry key="array-size" type="xint" value="48"/>
<config key="0">
<entry key="datacell" type="xstring" value="org.knime.core.data.def.StringCell"/>
<config key="org.knime.core.data.def.StringCell">
<entry key="StringCell" type="xstring" value="france,lyon,file:md5sum=291ee8560d7a38f283cdec130c6f216f,file:sha1sig=d639b399208df4397e73dfa3828d33a94a57fca1"/>
</config>
</config>
<config key="1">
<entry key="datacell" type="xstring" value="org.knime.core.data.def.StringCell"/>
<config key="org.knime.core.data.def.StringCell">
<entry key="StringCell" type="xstring" value="france,lyon,file:md5sum=da1e473075bdc73548b3ddc06e9f1778,file:sha1sig=aa5b7fa74d2140462b5e2ec33e3b179e3eaf079c"/>
</config>
</config>
<config key="2">
<entry key="datacell" type="xstring" value="org.knime.core.data.def.StringCell"/>
<config key="org.knime.core.data.def.StringCell">
<entry key="StringCell" type="xstring" value="france,lyon,file:md5sum=ff340bf8b62321462aca698737494351,file:sha1sig=5e8d5235884e69aa527679fe99aca7fb458c1a44"/>
</config>
</config>
<config key="3">
<entry key="datacell" type="xstring" value="org.knime.core.data.def.StringCell"/>
<config key="org.knime.core.data.def.StringCell">
<entry key="StringCell" type="xstring" value="france,lyon,file:md5sum=cb00bf1a041a9ff7230568465c8cdba0,file:sha1sig=80be60a134767b1a09dbc25a810f340f415428d8"/>
</config>
</config>
<config key="4">
<entry key="datacell" type="xstring" value="org.knime.core.data.def.StringCell"/>
<config key="org.knime.core.data.def.StringCell">
<entry key="StringCell" type="xstring" value="france,lyon,file:md5sum=6ce1bb23709daa6d21d578919b3f4c9a,file:sha1sig=d8b83ad38cdf01949dc094a3e464bbcb4d492fba"/>
</config>
</config>
<config key="5">
<entry key="datacell" type="xstring" value="org.knime.core.data.def.StringCell"/>
<config key="org.knime.core.data.def.StringCell">
<entry key="StringCell" type="xstring" value="france,lyon,file:md5sum=6ff7ed9a8205e5f531889c93df4be752,file:sha1sig=660a4e387608fbbade3247017fe03c308ed854d1"/>
</config>
</config>
<config key="6">
<entry key="datacell" type="xstring" value="org.knime.core.data.def.StringCell"/>
<config key="org.knime.core.data.def.StringCell">
<entry key="StringCell" type="xstring" value="france,lyon,file:md5sum=f1e7d420c69edd854d8a53f8ae674c8a,file:sha1sig=0ea9f8161ab4a746422d20d8a9df137d76163842"/>
</config>
</config>
<config key="7">
<entry key="datacell" type="xstring" value="org.knime.core.data.def.StringCell"/>
<config key="org.knime.core.data.def.StringCell">
<entry key="StringCell" type="xstring" value="france,lyon,file:md5sum=c4ee42961058fb3bf415e5fd8e73a4aa,file:sha1sig=6c4cabf13cf0f975b1329b6119da4df218f19a19"/>
</config>
</config>
<config key="8">
<entry key="datacell" type="xstring" value="org.knime.core.data.def.StringCell"/>
<config key="org.knime.core.data.def.StringCell">
<entry key="StringCell" type="xstring" value="france,lyon,file:md5sum=9c0ada79b665e24ea6b874517cea54bd,file:sha1sig=58ddc42d18bab9a3db3ca76a1c709dcbb06c03ec"/>
</config>
</config>
<config key="9">
<entry key="datacell" type="xstring" value="org.knime.core.data.def.StringCell"/>
<config key="org.knime.core.data.def.StringCell">
<entry key="StringCell" type="xstring" value="france,lyon,file:md5sum=076d7319669556d08bf9aae8feb9e84f,file:sha1sig=c7e508114d11dceadf71ec476ba0a93bb06f751b"/>
</config>
</config>
<config key="10">
<entry key="datacell" type="xstring" value="org.knime.core.data.def.StringCell"/>
<config key="org.knime.core.data.def.StringCell">
<entry key="StringCell" type="xstring" value="france,lyon,file:md5sum=77b6979f6dc43f1935ace9f027635355,file:sha1sig=1d8072c86e6460430b9adb97ce2955d0f14476cb"/>
</config>
</config>
<config key="11">
<entry key="datacell" type="xstring" value="org.knime.core.data.def.StringCell"/>
<config key="org.knime.core.data.def.StringCell">
<entry key="StringCell" type="xstring" value="france,lyon,file:md5sum=1ab4f0e8e20e4f5cee053b1062ee3378,file:sha1sig=f2ab55e3fcca6e39fc7c9bd8d2cfca5fafc5ce3b"/>
</config>
</config>
<config key="12">
<entry key="datacell" type="xstring" value="org.knime.core.data.def.StringCell"/>
<config key="org.knime.core.data.def.StringCell">
<entry key="StringCell" type="xstring" value="france,lyon,file:md5sum=ec338da7bbcf849bb6c5e20c96f050a6,file:sha1sig=61f18a94f5be9e3bf11a2c1433e4250e752f5a3f"/>
</config>
</config>
<config key="13">
<entry key="datacell" type="xstring" value="org.knime.core.data.def.StringCell"/>
<config key="org.knime.core.data.def.StringCell">
<entry key="StringCell" type="xstring" value="france,lyon,file:md5sum=5c99b7994f82a8eb1d746a86d4b00a96,file:sha1sig=f4493c35c085c929d224f176bb385e4a13d379d5"/>
</config>
</config>
<config key="14">
<entry key="datacell" type="xstring" value="org.knime.core.data.def.StringCell"/>
<config key="org.knime.core.data.def.StringCell">
<entry key="StringCell" type="xstring" value="france,lyon,file:md5sum=db7202ad28cb12d97cd6b1a7d1081bd3,file:sha1sig=861eec48a7d1df4b05820b3ef08dffdee45130b3"/>
</config>
</config>
<config key="15">
<entry key="datacell" type="xstring" value="org.knime.core.data.def.StringCell"/>
<config key="org.knime.core.data.def.StringCell">
<entry key="StringCell" type="xstring" value="france,lyon,file:md5sum=8606280b922f7c5643533fcc6fadaff8,file:sha1sig=ce116047098ec4c36b1a28d14139eab43348542a"/>
</config>
</config>
<config key="16">
<entry key="datacell" type="xstring" value="org.knime.core.data.def.StringCell"/>
<config key="org.knime.core.data.def.StringCell">
<entry key="StringCell" type="xstring" value="france,lyon,file:md5sum=f6f0d7b94165f7e9c6f6363a79f9a6c4,file:sha1sig=c311a34b7cdbf1f725e9c9574fe19686a8114ccb"/>
</config>
</config>
<config key="17">
<entry key="datacell" type="xstring" value="org.knime.core.data.def.StringCell"/>
<config key="org.knime.core.data.def.StringCell">
<entry key="StringCell" type="xstring" value="france,lyon,file:md5sum=513b532869dab3bfd3eec6c1d413add1,file:sha1sig=3827c7bc4507e3717c0f13282e78ea2114d4829d"/>
</config>
</config>
<config key="18">
<entry key="datacell" type="xstring" value="org.knime.core.data.def.StringCell"/>
<config key="org.knime.core.data.def.StringCell">
<entry key="StringCell" type="xstring" value="france,lyon,file:md5sum=65b6649412a7bdeeccb6ac7098e90a66,file:sha1sig=6d7cc992f2b5902808bf34157d8fbc5ce92b9765"/>
</config>
</config>
<config key="19">
<entry key="datacell" type="xstring" value="org.knime.core.data.def.StringCell"/>
<config key="org.knime.core.data.def.StringCell">
<entry key="StringCell" type="xstring" value="france,lyon,file:md5sum=58c64aa7e6810a002d4a532d6557b77a,file:sha1sig=43f3c7ea908df93356af56b6d0b77f3646f60d50"/>
</config>
</config>
<config key="20">
<entry key="datacell" type="xstring" value="org.knime.core.data.def.StringCell"/>
<config key="org.knime.core.data.def.StringCell">
<entry key="StringCell" type="xstring" value="france,lyon,file:md5sum=a6b45e41a36805ff2ad151682eed3100,file:sha1sig=e735f613106444810f2b38b6daca175ebed34d13"/>
</config>
</config>
<config key="21">
<entry key="datacell" type="xstring" value="org.knime.core.data.def.StringCell"/>
<config key="org.knime.core.data.def.StringCell">
<entry key="StringCell" type="xstring" value="france,lyon,file:md5sum=91430cc4e727ac4db7d4a30b7df992a9,file:sha1sig=6ea06a30292fc8e0e52712bda957bbbc1f9ec438"/>
</config>
</config>
<config key="22">
<entry key="datacell" type="xstring" value="org.knime.core.data.def.StringCell"/>
<config key="org.knime.core.data.def.StringCell">
<entry key="StringCell" type="xstring" value=""/>
</config>
</config>
<config key="23">
<entry key="datacell" type="xstring" value="org.knime.core.data.def.StringCell"/>
<config key="org.knime.core.data.def.StringCell">
<entry key="StringCell" type="xstring" value="france,europa,europe,lyon,francia,basílica,fourvière,ródanoalpes"/>
</config>
</config>
<config key="24">
<entry key="datacell" type="xstring" value="org.knime.core.data.def.StringCell"/>
<config key="org.knime.core.data.def.StringCell">
<entry key="StringCell" type="xstring" value="square,squareformat,iphoneography,instagramapp,uploaded:by=instagram"/>
</config>
</config>
<config key="25">
<entry key="datacell" type="xstring" value="org.knime.core.data.def.StringCell"/>
<config key="org.knime.core.data.def.StringCell">
<entry key="StringCell" type="xstring" value="building,verde,green,architecture,lyon,edificio,architettura,contemporanea,contemprary"/>
</config>
</config>
<config key="26">
<entry key="datacell" type="xstring" value="org.knime.core.data.def.StringCell"/>
<config key="org.knime.core.data.def.StringCell">
<entry key="StringCell" type="xstring" value="square,squareformat,iphoneography,instagramapp,uploaded:by=instagram,foursquare:venue=4e0462c82271233b767cec75"/>
</config>
</config>
<config key="27">
<entry key="datacell" type="xstring" value="org.knime.core.data.def.StringCell"/>
<config key="org.knime.core.data.def.StringCell">
<entry key="StringCell" type="xstring" value="back,le,future,to,delorean,dmc12,vers,futur,retour,the"/>
</config>
</config>
<config key="28">
<entry key="datacell" type="xstring" value="org.knime.core.data.def.StringCell"/>
<config key="org.knime.core.data.def.StringCell">
<entry key="StringCell" type="xstring" value="back,le,future,to,delorean,dmc12,vers,futur,hoverboard,retour,the"/>
</config>
</config>
<config key="29">
<entry key="datacell" type="xstring" value="org.knime.core.data.def.StringCell"/>
<config key="org.knime.core.data.def.StringCell">
<entry key="StringCell" type="xstring" value="france"/>
</config>
</config>
<config key="30">
<entry key="datacell" type="xstring" value="org.knime.core.data.def.StringCell"/>
<config key="org.knime.core.data.def.StringCell">
<entry key="StringCell" type="xstring" value="plant,france,green,canon,plante,de,eos,lyon,jardin,vert,rhône,ii,usm,polypodiaceae,botany,botanique,fr,botanicalgarden,ef,plantes,6d,jardinbotanique,platycerium,pteridophyta,2470mm,rhônealpes,f28l,filicopsida,vascularplant,parcbotanique,filicales,polypodiales,grammitidaceae,drynariaceae,canoneos6d,canonef2470mmf28liiusm,jardinbotaniquedelyon,jardinbotaniqueduparcdelatêtedor"/>
</config>
</config>
<config key="31">
<entry key="datacell" type="xstring" value="org.knime.core.data.def.StringCell"/>
<config key="org.knime.core.data.def.StringCell">
<entry key="StringCell" type="xstring" value="en,brown,france,canon,de,mammal,eos,zoo,la,lyon,jardin,rhône,ii,usm,marron,fr,parc,ef,ville,animalia,mammalia,animalpark,zoology,mammifère,6d,zoologique,vertebrates,2470mm,carnivora,rhônealpes,chordates,chordata,zoologicalgarden,f28l,metazoa,vertebrata,zoologicalpark,ailurus,parczoologique,captivité,jardinzoologique,animalincaptivity,ailuridae,chordés,canoneos6d,canonef2470mmf28liiusm,cordés,carnivoran,animalencaptivité,jardinzoologiquedelavilledelyon"/>
</config>
</config>
<config key="32">
<entry key="datacell" type="xstring" value="org.knime.core.data.def.StringCell"/>
<config key="org.knime.core.data.def.StringCell">
<entry key="StringCell" type="xstring" value="plant,france,green,yellow,jaune,canon,plante,de,eos,lyon,jardin,vert,rhône,ii,usm,botany,botanique,fr,botanicalgarden,ef,plantes,6d,jardinbotanique,dicotyledon,angiospermae,2470mm,floweringplants,rhônealpes,asteridae,magnoliophyta,magnoliidae,angiosperms,f28l,pedaliaceae,eudicots,uncarina,lamiales,vraies,asterids,dicotyledoneae,tracheobionta,vascularplant,parcbotanique,dicotylédones,dicotylédone,canoneos6d,eudicotyledons,canonef2470mmf28liiusm,angiospermes,jardinbotaniquedelyon,eudicotidae,astéridées,asteranae,dicotylédonesvraies,jardinbotaniqueduparcdelatêtedor"/>
</config>
</config>
<config key="33">
<entry key="datacell" type="xstring" value="org.knime.core.data.def.StringCell"/>
<config key="org.knime.core.data.def.StringCell">
<entry key="StringCell" type="xstring" value="white,france,green,public,canon,de,table,eos,la,chair,lyon,jardin,vert,rhône,ii,usm,dor,fr,parc,blanc,ef,chaise,tête,chessboard,municipalpark,6d,urbanpark,2470mm,metropolitanpark,publicpark,jardinpublic,rhônealpes,parcdelatêtedor,f28l,échiquier,publicopenspace,municipalgardens,parcurbain,canoneos6d,canonef2470mmf28liiusm"/>
</config>
</config>
<config key="34">
<entry key="datacell" type="xstring" value="org.knime.core.data.def.StringCell"/>
<config key="org.knime.core.data.def.StringCell">
<entry key="StringCell" type="xstring" value="stilllife,jack,naturemorte,coloquinte"/>
</config>
</config>
<config key="35">
<entry key="datacell" type="xstring" value="org.knime.core.data.def.StringCell"/>
<config key="org.knime.core.data.def.StringCell">
<entry key="StringCell" type="xstring" value="square,squareformat,iphoneography,instagramapp,xproii,uploaded:by=instagram,foursquare:venue=4e0462c82271233b767cec75"/>
</config>
</config>
<config key="36">
<entry key="datacell" type="xstring" value="org.knime.core.data.def.StringCell"/>
<config key="org.knime.core.data.def.StringCell">
<entry key="StringCell" type="xstring" value="stilllife,rave,naturemorte,racines,navet"/>
</config>
</config>
<config key="37">
<entry key="datacell" type="xstring" value="org.knime.core.data.def.StringCell"/>
<config key="org.knime.core.data.def.StringCell">
<entry key="StringCell" type="xstring" value="pink,plant,france,rose,canon,plante,de,eos,lyon,jardin,rhône,peony,ii,usm,botany,botanique,fr,botanicalgarden,ef,6d,jardinbotanique,pivoine,paeonia,dicotyledon,angiospermae,2470mm,floweringplants,saxifragales,rhônealpes,paeoniaceae,magnoliophyta,magnoliidae,angiosperms,f28l,eudicots,vraies,dicotyledoneae,tracheobionta,vascularplant,parcbotanique,dicotylédones,dicotylédone,canoneos6d,eudicotyledons,canonef2470mmf28liiusm,angiospermes,jardinbotaniquedelyon,eudicotidae,dicotylédonesvraies,paéoniacées,jardinbotaniqueduparcdelatêtedor"/>
</config>
</config>
<config key="38">
<entry key="datacell" type="xstring" value="org.knime.core.data.def.StringCell"/>
<config key="org.knime.core.data.def.StringCell">
<entry key="StringCell" type="xstring" value="france,statue,night,self,one,michael,october,lyon,nuit,weight,ingar,elmgreen,dragset,2015"/>
</config>
</config>
<config key="39">
<entry key="datacell" type="xstring" value="org.knime.core.data.def.StringCell"/>
<config key="org.knime.core.data.def.StringCell">
<entry key="StringCell" type="xstring" value="world,france,night,french,stand,october,lyon,magic,papa,nuit,français,barbe,crêpes,2015,barbeàpapa"/>
</config>
</config>
<config key="40">
<entry key="datacell" type="xstring" value="org.knime.core.data.def.StringCell"/>
<config key="org.knime.core.data.def.StringCell">
<entry key="StringCell" type="xstring" value="france,night,de,october,tour,lyon,horloge,nuit,octobre,charité,hôpital,lhorloge,2015"/>
</config>
</config>
<config key="41">
<entry key="datacell" type="xstring" value="org.knime.core.data.def.StringCell"/>
<config key="org.knime.core.data.def.StringCell">
<entry key="StringCell" type="xstring" value="square,squareformat,hudson,iphoneography,instagramapp,uploaded:by=instagram"/>
</config>
</config>
<config key="42">
<entry key="datacell" type="xstring" value="org.knime.core.data.def.StringCell"/>
<config key="org.knime.core.data.def.StringCell">
<entry key="StringCell" type="xstring" value="cactus,plant,france,green,canon,plante,de,eos,lyon,jardin,vert,rhône,ii,usm,opuntia,cactaceae,botany,botanique,fr,botanicalgarden,ef,cactées,6d,jardinbotanique,dicotyledon,angiospermae,2470mm,floweringplants,rhônealpes,magnoliophyta,magnoliidae,caryophyllales,angiosperms,f28l,eudicots,vraies,dicotyledoneae,tracheobionta,vascularplant,parcbotanique,dicotylédones,cactacées,dicotylédone,cactusraquette,canoneos6d,eudicotyledons,canonef2470mmf28liiusm,angiospermes,jardinbotaniquedelyon,eudicotidae,dicotylédonesvraies,jardinbotaniqueduparcdelatêtedor"/>
</config>
</config>
<config key="43">
<entry key="datacell" type="xstring" value="org.knime.core.data.def.StringCell"/>
<config key="org.knime.core.data.def.StringCell">
<entry key="StringCell" type="xstring" value="red,plant,france,green,yellow,jaune,canon,plante,de,rouge,eos,lyon,jardin,vert,rhône,ii,usm,botany,botanique,fr,botanicalgarden,heliconia,ef,6d,jardinbotanique,monocotyledoneae,2470mm,rhônealpes,lobsterclaws,heliconiaceae,zingiberales,zingiberidae,f28l,parcbotanique,falsebirdofparadise,canoneos6d,monocotylédone,héliconia,canonef2470mmf28liiusm,wildplantains,angiospermes,jardinbotaniquedelyon,jardinbotaniqueduparcdelatêtedor"/>
</config>
</config>
<config key="44">
<entry key="datacell" type="xstring" value="org.knime.core.data.def.StringCell"/>
<config key="org.knime.core.data.def.StringCell">
<entry key="StringCell" type="xstring" value="plant,france,green,yellow,jaune,canon,plante,de,eos,lyon,jardin,vert,rhône,ii,usm,botany,botanique,fr,botanicalgarden,ef,6d,jardinbotanique,dicotyledon,angiospermae,2470mm,floweringplants,rhônealpes,asteridae,magnoliophyta,magnoliidae,angiosperms,f28l,pedaliaceae,eudicots,uncarina,lamiales,vraies,asterids,dicotyledoneae,tracheobionta,vascularplant,parcbotanique,dicotylédones,dicotylédone,canoneos6d,eudicotyledons,canonef2470mmf28liiusm,angiospermes,jardinbotaniquedelyon,eudicotidae,astéridées,asteranae,dicotylédonesvraies,jardinbotaniqueduparcdelatêtedor"/>
</config>
</config>
<config key="45">
<entry key="datacell" type="xstring" value="org.knime.core.data.def.StringCell"/>
<config key="org.knime.core.data.def.StringCell">
<entry key="StringCell" type="xstring" value="en,france,bird,canon,de,eos,grey,zoo,gris,la,lyon,gray,jardin,aves,rhône,ii,usm,fr,parc,oiseau,ef,ville,animalia,rhea,animalpark,zoology,6d,zoologique,vertebrates,2470mm,rhônealpes,chordates,chordata,zoologicalgarden,f28l,metazoa,vertebrata,zoologicalpark,parczoologique,captivité,jardinzoologique,animalincaptivity,rheidae,rheiformes,chordés,canoneos6d,canonef2470mmf28liiusm,cordés,animalencaptivité,jardinzoologiquedelavilledelyon"/>
</config>
</config>
<config key="46">
<entry key="datacell" type="xstring" value="org.knime.core.data.def.StringCell"/>
<config key="org.knime.core.data.def.StringCell">
<entry key="StringCell" type="xstring" value="france,building,scale,arquitetura,stairs,arquitectura,lyon,lione,edificio,frança,escada,palazzo,francia,bâtiment,condominio,architettura,escalier,predio,rhônealpes,courdesvoraces,escaliera"/>
</config>
</config>
<config key="47">
<entry key="datacell" type="xstring" value="org.knime.core.data.def.StringCell"/>
<config key="org.knime.core.data.def.StringCell">
<entry key="StringCell" type="xstring" value="france,120,6x6,film,colors,mediumformat,holidays,colore,lyon,kodak,lione,august,agosto,squareformat,analogue,filmcamera,passage,francia,yashica,vacanze,analogica,croixrousse,2015,pellicola,analogico,rullino,medioformato"/>
</config>
</config>
</config>
</config>
<config key="column_properties"/>
<config key="meta_data"/>
</config>
<config key="column_spec_5">
<entry key="column_name" type="xstring" value="title"/>
<config key="element_names">
<entry key="array-size" type="xint" value="0"/>
</config>
<config key="column_type">
<entry key="cell_class" type="xstring" value="org.knime.core.data.def.StringCell"/>
</config>
<config key="column_domain">
<config key="possible_values">
<entry key="array-size" type="xint" value="41"/>
<config key="0">
<entry key="datacell" type="xstring" value="org.knime.core.data.def.StringCell"/>
<config key="org.knime.core.data.def.StringCell">
<entry key="StringCell" type="xstring" value="Ancient Theatre of Fourvière"/>
</config>
</config>
<config key="1">
<entry key="datacell" type="xstring" value="org.knime.core.data.def.StringCell"/>
<config key="org.knime.core.data.def.StringCell">
<entry key="StringCell" type="xstring" value="Basilica of Notre-Dame de Fourvière"/>
</config>
</config>
<config key="2">
<entry key="datacell" type="xstring" value="org.knime.core.data.def.StringCell"/>
<config key="org.knime.core.data.def.StringCell">
<entry key="StringCell" type="xstring" value="Lyon"/>
</config>
</config>
<config key="3">
<entry key="datacell" type="xstring" value="org.knime.core.data.def.StringCell"/>
<config key="org.knime.core.data.def.StringCell">
<entry key="StringCell" type="xstring" value="Saône in Lyon"/>
</config>
</config>
<config key="4">
<entry key="datacell" type="xstring" value="org.knime.core.data.def.StringCell"/>
<config key="org.knime.core.data.def.StringCell">
<entry key="StringCell" type="xstring" value="Basílica Notre-Dame de Fourvière"/>
</config>
</config>
<config key="5">
<entry key="datacell" type="xstring" value="org.knime.core.data.def.StringCell"/>
<config key="org.knime.core.data.def.StringCell">
<entry key="StringCell" type="xstring" value="vélo fantôme"/>
</config>
</config>
<config key="6">
<entry key="datacell" type="xstring" value="org.knime.core.data.def.StringCell"/>
<config key="org.knime.core.data.def.StringCell">
<entry key="StringCell" type="xstring" value="tout est mini dans notre vie"/>
</config>
</config>
<config key="7">
<entry key="datacell" type="xstring" value="org.knime.core.data.def.StringCell"/>
<config key="org.knime.core.data.def.StringCell">
<entry key="StringCell" type="xstring" value="rencontre Stendhalienne"/>
</config>
</config>
<config key="8">
<entry key="datacell" type="xstring" value="org.knime.core.data.def.StringCell"/>
<config key="org.knime.core.data.def.StringCell">
<entry key="StringCell" type="xstring" value="non, tu ne rouleras pas !"/>
</config>
</config>
<config key="9">
<entry key="datacell" type="xstring" value="org.knime.core.data.def.StringCell"/>
<config key="org.knime.core.data.def.StringCell">
<entry key="StringCell" type="xstring" value="Trop cool @addbike.  Entreprendre c'est ça : donner vie à ses idées. Créer.  Bravo. #startup #Qwestly"/>
</config>
</config>
<config key="10">
<entry key="datacell" type="xstring" value="org.knime.core.data.def.StringCell"/>
<config key="org.knime.core.data.def.StringCell">
<entry key="StringCell" type="xstring" value="Nouvelles cartes reçues à temps pour le #blendwebmix"/>
</config>
</config>
<config key="11">
<entry key="datacell" type="xstring" value="org.knime.core.data.def.StringCell"/>
<config key="org.knime.core.data.def.StringCell">
<entry key="StringCell" type="xstring" value="IMG_7256"/>
</config>
</config>
<config key="12">
<entry key="datacell" type="xstring" value="org.knime.core.data.def.StringCell"/>
<config key="org.knime.core.data.def.StringCell">
<entry key="StringCell" type="xstring" value="IMG_7255"/>
</config>
</config>
<config key="13">
<entry key="datacell" type="xstring" value="org.knime.core.data.def.StringCell"/>
<config key="org.knime.core.data.def.StringCell">
<entry key="StringCell" type="xstring" value="IMG_7254"/>
</config>
</config>
<config key="14">
<entry key="datacell" type="xstring" value="org.knime.core.data.def.StringCell"/>
<config key="org.knime.core.data.def.StringCell">
<entry key="StringCell" type="xstring" value="IMG_7253"/>
</config>
</config>
<config key="15">
<entry key="datacell" type="xstring" value="org.knime.core.data.def.StringCell"/>
<config key="org.knime.core.data.def.StringCell">
<entry key="StringCell" type="xstring" value="IMG_7260"/>
</config>
</config>
<config key="16">
<entry key="datacell" type="xstring" value="org.knime.core.data.def.StringCell"/>
<config key="org.knime.core.data.def.StringCell">
<entry key="StringCell" type="xstring" value="IMG_7261"/>
</config>
</config>
<config key="17">
<entry key="datacell" type="xstring" value="org.knime.core.data.def.StringCell"/>
<config key="org.knime.core.data.def.StringCell">
<entry key="StringCell" type="xstring" value="IMG_7262"/>
</config>
</config>
<config key="18">
<entry key="datacell" type="xstring" value="org.knime.core.data.def.StringCell"/>
<config key="org.knime.core.data.def.StringCell">
<entry key="StringCell" type="xstring" value="IMG_7264"/>
</config>
</config>
<config key="19">
<entry key="datacell" type="xstring" value="org.knime.core.data.def.StringCell"/>
<config key="org.knime.core.data.def.StringCell">
<entry key="StringCell" type="xstring" value="IMG_7267"/>
</config>
</config>
<config key="20">
<entry key="datacell" type="xstring" value="org.knime.core.data.def.StringCell"/>
<config key="org.knime.core.data.def.StringCell">
<entry key="StringCell" type="xstring" value="IMG_7268"/>
</config>
</config>
<config key="21">
<entry key="datacell" type="xstring" value="org.knime.core.data.def.StringCell"/>
<config key="org.knime.core.data.def.StringCell">
<entry key="StringCell" type="xstring" value="IMG_7272"/>
</config>
</config>
<config key="22">
<entry key="datacell" type="xstring" value="org.knime.core.data.def.StringCell"/>
<config key="org.knime.core.data.def.StringCell">
<entry key="StringCell" type="xstring" value="a church"/>
</config>
</config>
<config key="23">
<entry key="datacell" type="xstring" value="org.knime.core.data.def.StringCell"/>
<config key="org.knime.core.data.def.StringCell">
<entry key="StringCell" type="xstring" value="Platycerium bifurcatum (Corne d'élan)"/>
</config>
</config>
<config key="24">
<entry key="datacell" type="xstring" value="org.knime.core.data.def.StringCell"/>
<config key="org.knime.core.data.def.StringCell">
<entry key="StringCell" type="xstring" value="Ailurus fulgens (Panda roux)"/>
</config>
</config>
<config key="25">
<entry key="datacell" type="xstring" value="org.knime.core.data.def.StringCell"/>
<config key="org.knime.core.data.def.StringCell">
<entry key="StringCell" type="xstring" value="Uncarina grandidieri"/>
</config>
</config>
<config key="26">
<entry key="datacell" type="xstring" value="org.knime.core.data.def.StringCell"/>
<config key="org.knime.core.data.def.StringCell">
<entry key="StringCell" type="xstring" value="Table échiquier"/>
</config>
</config>
<config key="27">
<entry key="datacell" type="xstring" value="org.knime.core.data.def.StringCell"/>
<config key="org.knime.core.data.def.StringCell">
<entry key="StringCell" type="xstring" value="Coloquinte et Jack be little"/>
</config>
</config>
<config key="28">
<entry key="datacell" type="xstring" value="org.knime.core.data.def.StringCell"/>
<config key="org.knime.core.data.def.StringCell">
<entry key="StringCell" type="xstring" value="#selfirme #suitup"/>
</config>
</config>
<config key="29">
<entry key="datacell" type="xstring" value="org.knime.core.data.def.StringCell"/>
<config key="org.knime.core.data.def.StringCell">
<entry key="StringCell" type="xstring" value="Racines d'automne"/>
</config>
</config>
<config key="30">
<entry key="datacell" type="xstring" value="org.knime.core.data.def.StringCell"/>
<config key="org.knime.core.data.def.StringCell">
<entry key="StringCell" type="xstring" value="Paeonia lactiflora 'La Perle' (Pivoine de Chine 'La Perle')"/>
</config>
</config>
<config key="31">
<entry key="datacell" type="xstring" value="org.knime.core.data.def.StringCell"/>
<config key="org.knime.core.data.def.StringCell">
<entry key="StringCell" type="xstring" value="Lyon 19 October 2015 102"/>
</config>
</config>
<config key="32">
<entry key="datacell" type="xstring" value="org.knime.core.data.def.StringCell"/>
<config key="org.knime.core.data.def.StringCell">
<entry key="StringCell" type="xstring" value="Lyon 19 October 2015 075"/>
</config>
</config>
<config key="33">
<entry key="datacell" type="xstring" value="org.knime.core.data.def.StringCell"/>
<config key="org.knime.core.data.def.StringCell">
<entry key="StringCell" type="xstring" value="Lyon 19 October 2015 063"/>
</config>
</config>
<config key="34">
<entry key="datacell" type="xstring" value="org.knime.core.data.def.StringCell"/>
<config key="org.knime.core.data.def.StringCell">
<entry key="StringCell" type="xstring" value="Je suis en retard pour le taf #suitup"/>
</config>
</config>
<config key="35">
<entry key="datacell" type="xstring" value="org.knime.core.data.def.StringCell"/>
<config key="org.knime.core.data.def.StringCell">
<entry key="StringCell" type="xstring" value="Opuntia quimilo"/>
</config>
</config>
<config key="36">
<entry key="datacell" type="xstring" value="org.knime.core.data.def.StringCell"/>
<config key="org.knime.core.data.def.StringCell">
<entry key="StringCell" type="xstring" value="Heliconia Rostrata"/>
</config>
</config>
<config key="37">
<entry key="datacell" type="xstring" value="org.knime.core.data.def.StringCell"/>
<config key="org.knime.core.data.def.StringCell">
<entry key="StringCell" type="xstring" value="Uncarina roeoesliana"/>
</config>
</config>
<config key="38">
<entry key="datacell" type="xstring" value="org.knime.core.data.def.StringCell"/>
<config key="org.knime.core.data.def.StringCell">
<entry key="StringCell" type="xstring" value="Rhea pennata (Nandou de Darwin)"/>
</config>
</config>
<config key="39">
<entry key="datacell" type="xstring" value="org.knime.core.data.def.StringCell"/>
<config key="org.knime.core.data.def.StringCell">
<entry key="StringCell" type="xstring" value="escher's stairs"/>
</config>
</config>
<config key="40">
<entry key="datacell" type="xstring" value="org.knime.core.data.def.StringCell"/>
<config key="org.knime.core.data.def.StringCell">
<entry key="StringCell" type="xstring" value="el vy (lione06)"/>
</config>
</config>
</config>
</config>
<config key="column_properties"/>
<config key="meta_data"/>
</config>
<config key="column_spec_6">
<entry key="column_name" type="xstring" value="date_taken_minute"/>
<config key="element_names">
<entry key="array-size" type="xint" value="0"/>
</config>
<config key="column_type">
<entry key="cell_class" type="xstring" value="org.knime.core.data.def.IntCell"/>
</config>
<config key="column_domain">
<config key="lower_bound">
<entry key="datacell" type="xstring" value="org.knime.core.data.def.IntCell"/>
<config key="org.knime.core.data.def.IntCell">
<entry key="IntCell" type="xint" value="0"/>
</config>
</config>
<config key="upper_bound">
<entry key="datacell" type="xstring" value="org.knime.core.data.def.IntCell"/>
<config key="org.knime.core.data.def.IntCell">
<entry key="IntCell" type="xint" value="59"/>
</config>
</config>
</config>
<config key="column_properties"/>
<config key="meta_data"/>
</config>
<config key="column_spec_7">
<entry key="column_name" type="xstring" value="date_taken_hour"/>
<config key="element_names">
<entry key="array-size" type="xint" value="0"/>
</config>
<config key="column_type">
<entry key="cell_class" type="xstring" value="org.knime.core.data.def.IntCell"/>
</config>
<config key="column_domain">
<config key="lower_bound">
<entry key="datacell" type="xstring" value="org.knime.core.data.def.IntCell"/>
<config key="org.knime.core.data.def.IntCell">
<entry key="IntCell" type="xint" value="0"/>
</config>
</config>
<config key="upper_bound">
<entry key="datacell" type="xstring" value="org.knime.core.data.def.IntCell"/>
<config key="org.knime.core.data.def.IntCell">
<entry key="IntCell" type="xint" value="23"/>
</config>
</config>
</config>
<config key="column_properties"/>
<config key="meta_data"/>
</config>
<config key="column_spec_8">
<entry key="column_name" type="xstring" value="date_taken_day"/>
<config key="element_names">
<entry key="array-size" type="xint" value="0"/>
</config>
<config key="column_type">
<entry key="cell_class" type="xstring" value="org.knime.core.data.def.IntCell"/>
</config>
<config key="column_domain">
<config key="lower_bound">
<entry key="datacell" type="xstring" value="org.knime.core.data.def.IntCell"/>
<config key="org.knime.core.data.def.IntCell">
<entry key="IntCell" type="xint" value="1"/>
</config>
</config>
<config key="upper_bound">
<entry key="datacell" type="xstring" value="org.knime.core.data.def.IntCell"/>
<config key="org.knime.core.data.def.IntCell">
<entry key="IntCell" type="xint" value="31"/>
</config>
</config>
</config>
<config key="column_properties"/>
<config key="meta_data"/>
</config>
<config key="column_spec_9">
<entry key="column_name" type="xstring" value="date_taken_month"/>
<config key="element_names">
<entry key="array-size" type="xint" value="0"/>
</config>
<config key="column_type">
<entry key="cell_class" type="xstring" value="org.knime.core.data.def.IntCell"/>
</config>
<config key="column_domain">
<config key="lower_bound">
<entry key="datacell" type="xstring" value="org.knime.core.data.def.IntCell"/>
<config key="org.knime.core.data.def.IntCell">
<entry key="IntCell" type="xint" value="1"/>
</config>
</config>
<config key="upper_bound">
<entry key="datacell" type="xstring" value="org.knime.core.data.def.IntCell"/>
<config key="org.knime.core.data.def.IntCell">
<entry key="IntCell" type="xint" value="12"/>
</config>
</config>
</config>
<config key="column_properties"/>
<config key="meta_data"/>
</config>
<config key="column_spec_10">
<entry key="column_name" type="xstring" value="date_taken_year"/>
<config key="element_names">
<entry key="array-size" type="xint" value="0"/>
</config>
<config key="column_type">
<entry key="cell_class" type="xstring" value="org.knime.core.data.def.IntCell"/>
</config>
<config key="column_domain">
<config key="lower_bound">
<entry key="datacell" type="xstring" value="org.knime.core.data.def.IntCell"/>
<config key="org.knime.core.data.def.IntCell">
<entry key="IntCell" type="xint" value="1957"/>
</config>
</config>
<config key="upper_bound">
<entry key="datacell" type="xstring" value="org.knime.core.data.def.IntCell"/>
<config key="org.knime.core.data.def.IntCell">
<entry key="IntCell" type="xint" value="2015"/>
</config>
</config>
</config>
<config key="column_properties"/>
<config key="meta_data"/>
</config>
<config key="column_spec_11">
<entry key="column_name" type="xstring" value="date_upload_minute"/>
<config key="element_names">
<entry key="array-size" type="xint" value="0"/>
</config>
<config key="column_type">
<entry key="cell_class" type="xstring" value="org.knime.core.data.def.IntCell"/>
</config>
<config key="column_domain">
<config key="lower_bound">
<entry key="datacell" type="xstring" value="org.knime.core.data.def.IntCell"/>
<config key="org.knime.core.data.def.IntCell">
<entry key="IntCell" type="xint" value="0"/>
</config>
</config>
<config key="upper_bound">
<entry key="datacell" type="xstring" value="org.knime.core.data.def.IntCell"/>
<config key="org.knime.core.data.def.IntCell">
<entry key="IntCell" type="xint" value="59"/>
</config>
</config>
</config>
<config key="column_properties"/>
<config key="meta_data"/>
</config>
<config key="column_spec_12">
<entry key="column_name" type="xstring" value="date_upload_hour"/>
<config key="element_names">
<entry key="array-size" type="xint" value="0"/>
</config>
<config key="column_type">
<entry key="cell_class" type="xstring" value="org.knime.core.data.def.IntCell"/>
</config>
<config key="column_domain">
<config key="lower_bound">
<entry key="datacell" type="xstring" value="org.knime.core.data.def.IntCell"/>
<config key="org.knime.core.data.def.IntCell">
<entry key="IntCell" type="xint" value="0"/>
</config>
</config>
<config key="upper_bound">
<entry key="datacell" type="xstring" value="org.knime.core.data.def.IntCell"/>
<config key="org.knime.core.data.def.IntCell">
<entry key="IntCell" type="xint" value="23"/>
</config>
</config>
</config>
<config key="column_properties"/>
<config key="meta_data"/>
</config>
<config key="column_spec_13">
<entry key="column_name" type="xstring" value="date_upload_day"/>
<config key="element_names">
<entry key="array-size" type="xint" value="0"/>
</config>
<config key="column_type">
<entry key="cell_class" type="xstring" value="org.knime.core.data.def.IntCell"/>
</config>
<config key="column_domain">
<config key="lower_bound">
<entry key="datacell" type="xstring" value="org.knime.core.data.def.IntCell"/>
<config key="org.knime.core.data.def.IntCell">
<entry key="IntCell" type="xint" value="1"/>
</config>
</config>
<config key="upper_bound">
<entry key="datacell" type="xstring" value="org.knime.core.data.def.IntCell"/>
<config key="org.knime.core.data.def.IntCell">
<entry key="IntCell" type="xint" value="31"/>
</config>
</config>
</config>
<config key="column_properties"/>
<config key="meta_data"/>
</config>
<config key="column_spec_14">
<entry key="column_name" type="xstring" value="date_upload_month"/>
<config key="element_names">
<entry key="array-size" type="xint" value="0"/>
</config>
<config key="column_type">
<entry key="cell_class" type="xstring" value="org.knime.core.data.def.IntCell"/>
</config>
<config key="column_domain">
<config key="lower_bound">
<entry key="datacell" type="xstring" value="org.knime.core.data.def.IntCell"/>
<config key="org.knime.core.data.def.IntCell">
<entry key="IntCell" type="xint" value="1"/>
</config>
</config>
<config key="upper_bound">
<entry key="datacell" type="xstring" value="org.knime.core.data.def.IntCell"/>
<config key="org.knime.core.data.def.IntCell">
<entry key="IntCell" type="xint" value="11"/>
</config>
</config>
</config>
<config key="column_properties"/>
<config key="meta_data"/>
</config>
<config key="column_spec_15">
<entry key="column_name" type="xstring" value="date_upload_year"/>
<config key="element_names">
<entry key="array-size" type="xint" value="0"/>
</config>
<config key="column_type">
<entry key="cell_class" type="xstring" value="org.knime.core.data.def.IntCell"/>
</config>
<config key="column_domain">
<config key="lower_bound">
<entry key="datacell" type="xstring" value="org.knime.core.data.def.IntCell"/>
<config key="org.knime.core.data.def.IntCell">
<entry key="IntCell" type="xint" value="2014"/>
</config>
</config>
<config key="upper_bound">
<entry key="datacell" type="xstring" value="org.knime.core.data.def.IntCell"/>
<config key="org.knime.core.data.def.IntCell">
<entry key="IntCell" type="xint" value="2015"/>
</config>
</config>
</config>
<config key="column_properties"/>
<config key="meta_data"/>
</config>
</config>
