<?xml version="1.0" encoding="UTF-8"?>
<config xmlns="http://www.knime.org/2008/09/XMLConfig" xmlns:xsi="http://www.w3.org/2001/XMLSchema-instance" xsi:schemaLocation="http://www.knime.org/2008/09/XMLConfig http://www.knime.org/XMLConfig_2008_09.xsd" key="spec.xml">
<entry key="spec_name" type="xstring" value="default"/>
<entry key="number_columns" type="xint" value="16"/>
<config key="column_spec_0">
<entry key="column_name" type="xstring" value="id"/>
<config key="element_names">
<entry key="array-size" type="xint" value="0"/>
</config>
<config key="column_type">
<entry key="cell_class" type="xstring" value="org.knime.core.data.def.DoubleCell"/>
</config>
<config key="column_domain">
<config key="lower_bound">
<entry key="datacell" type="xstring" value="org.knime.core.data.def.DoubleCell"/>
<config key="org.knime.core.data.def.DoubleCell">
<entry key="DoubleCell" type="xdouble" value="3.06667535E8"/>
</config>
</config>
<config key="upper_bound">
<entry key="datacell" type="xstring" value="org.knime.core.data.def.DoubleCell"/>
<config key="org.knime.core.data.def.DoubleCell">
<entry key="DoubleCell" type="xdouble" value="2.3300580095E10"/>
</config>
</config>
</config>
<config key="column_properties"/>
<config key="meta_data"/>
</config>
<config key="column_spec_1">
<entry key="column_name" type="xstring" value="user"/>
<config key="element_names">
<entry key="array-size" type="xint" value="0"/>
</config>
<config key="column_type">
<entry key="cell_class" type="xstring" value="org.knime.core.data.def.StringCell"/>
</config>
<config key="column_domain">
<config key="possible_values">
<entry key="array-size" type="xint" value="17"/>
<config key="0">
<entry key="datacell" type="xstring" value="org.knime.core.data.def.StringCell"/>
<config key="org.knime.core.data.def.StringCell">
<entry key="StringCell" type="xstring" value="29248605@N07"/>
</config>
</config>
<config key="1">
<entry key="datacell" type="xstring" value="org.knime.core.data.def.StringCell"/>
<config key="org.knime.core.data.def.StringCell">
<entry key="StringCell" type="xstring" value="58207948@N03"/>
</config>
</config>
<config key="2">
<entry key="datacell" type="xstring" value="org.knime.core.data.def.StringCell"/>
<config key="org.knime.core.data.def.StringCell">
<entry key="StringCell" type="xstring" value="21806934@N03"/>
</config>
</config>
<config key="3">
<entry key="datacell" type="xstring" value="org.knime.core.data.def.StringCell"/>
<config key="org.knime.core.data.def.StringCell">
<entry key="StringCell" type="xstring" value="90493526@N00"/>
</config>
</config>
<config key="4">
<entry key="datacell" type="xstring" value="org.knime.core.data.def.StringCell"/>
<config key="org.knime.core.data.def.StringCell">
<entry key="StringCell" type="xstring" value="7423705@N02"/>
</config>
</config>
<config key="5">
<entry key="datacell" type="xstring" value="org.knime.core.data.def.StringCell"/>
<config key="org.knime.core.data.def.StringCell">
<entry key="StringCell" type="xstring" value="58672892@N06"/>
</config>
</config>
<config key="6">
<entry key="datacell" type="xstring" value="org.knime.core.data.def.StringCell"/>
<config key="org.knime.core.data.def.StringCell">
<entry key="StringCell" type="xstring" value="113111723@N02"/>
</config>
</config>
<config key="7">
<entry key="datacell" type="xstring" value="org.knime.core.data.def.StringCell"/>
<config key="org.knime.core.data.def.StringCell">
<entry key="StringCell" type="xstring" value="78873869@N03"/>
</config>
</config>
<config key="8">
<entry key="datacell" type="xstring" value="org.knime.core.data.def.StringCell"/>
<config key="org.knime.core.data.def.StringCell">
<entry key="StringCell" type="xstring" value="102989725@N04"/>
</config>
</config>
<config key="9">
<entry key="datacell" type="xstring" value="org.knime.core.data.def.StringCell"/>
<config key="org.knime.core.data.def.StringCell">
<entry key="StringCell" type="xstring" value="54635175@N03"/>
</config>
</config>
<config key="10">
<entry key="datacell" type="xstring" value="org.knime.core.data.def.StringCell"/>
<config key="org.knime.core.data.def.StringCell">
<entry key="StringCell" type="xstring" value="57314912@N03"/>
</config>
</config>
<config key="11">
<entry key="datacell" type="xstring" value="org.knime.core.data.def.StringCell"/>
<config key="org.knime.core.data.def.StringCell">
<entry key="StringCell" type="xstring" value="94398465@N00"/>
</config>
</config>
<config key="12">
<entry key="datacell" type="xstring" value="org.knime.core.data.def.StringCell"/>
<config key="org.knime.core.data.def.StringCell">
<entry key="StringCell" type="xstring" value="76692842@N07"/>
</config>
</config>
<config key="13">
<entry key="datacell" type="xstring" value="org.knime.core.data.def.StringCell"/>
<config key="org.knime.core.data.def.StringCell">
<entry key="StringCell" type="xstring" value="38775193@N06"/>
</config>
</config>
<config key="14">
<entry key="datacell" type="xstring" value="org.knime.core.data.def.StringCell"/>
<config key="org.knime.core.data.def.StringCell">
<entry key="StringCell" type="xstring" value="66063379@N03"/>
</config>
</config>
<config key="15">
<entry key="datacell" type="xstring" value="org.knime.core.data.def.StringCell"/>
<config key="org.knime.core.data.def.StringCell">
<entry key="StringCell" type="xstring" value="92849559@N04"/>
</config>
</config>
<config key="16">
<entry key="datacell" type="xstring" value="org.knime.core.data.def.StringCell"/>
<config key="org.knime.core.data.def.StringCell">
<entry key="StringCell" type="xstring" value="48551155@N05"/>
</config>
</config>
</config>
</config>
<config key="column_properties"/>
<config key="meta_data"/>
</config>
<config key="column_spec_2">
<entry key="column_name" type="xstring" value="lat"/>
<config key="element_names">
<entry key="array-size" type="xint" value="0"/>
</config>
<config key="column_type">
<entry key="cell_class" type="xstring" value="org.knime.core.data.def.DoubleCell"/>
</config>
<config key="column_domain">
<config key="lower_bound">
<entry key="datacell" type="xstring" value="org.knime.core.data.def.DoubleCell"/>
<config key="org.knime.core.data.def.DoubleCell">
<entry key="DoubleCell" type="xdouble" value="45.475833"/>
</config>
</config>
<config key="upper_bound">
<entry key="datacell" type="xstring" value="org.knime.core.data.def.DoubleCell"/>
<config key="org.knime.core.data.def.DoubleCell">
<entry key="DoubleCell" type="xdouble" value="46.040333"/>
</config>
</config>
</config>
<config key="column_properties"/>
<config key="meta_data"/>
</config>
<config key="column_spec_3">
<entry key="column_name" type="xstring" value="long"/>
<config key="element_names">
<entry key="array-size" type="xint" value="0"/>
</config>
<config key="column_type">
<entry key="cell_class" type="xstring" value="org.knime.core.data.def.DoubleCell"/>
</config>
<config key="column_domain">
<config key="lower_bound">
<entry key="datacell" type="xstring" value="org.knime.core.data.def.DoubleCell"/>
<config key="org.knime.core.data.def.DoubleCell">
<entry key="DoubleCell" type="xdouble" value="4.442983"/>
</config>
</config>
<config key="upper_bound">
<entry key="datacell" type="xstring" value="org.knime.core.data.def.DoubleCell"/>
<config key="org.knime.core.data.def.DoubleCell">
<entry key="DoubleCell" type="xdouble" value="5.21667"/>
</config>
</config>
</config>
<config key="column_properties"/>
<config key="meta_data"/>
</config>
<config key="column_spec_4">
<entry key="column_name" type="xstring" value="tags"/>
<config key="element_names">
<entry key="array-size" type="xint" value="0"/>
</config>
<config key="column_type">
<entry key="cell_class" type="xstring" value="org.knime.core.data.def.StringCell"/>
</config>
<config key="column_domain">
<config key="possible_values">
<entry key="array-size" type="xint" value="28"/>
<config key="0">
<entry key="datacell" type="xstring" value="org.knime.core.data.def.StringCell"/>
<config key="org.knime.core.data.def.StringCell">
<entry key="StringCell" type="xstring" value="sculpture,lyon,caïn,etex,antoineetex,muséedesbeauxartsdelyon"/>
</config>
</config>
<config key="1">
<entry key="datacell" type="xstring" value="org.knime.core.data.def.StringCell"/>
<config key="org.knime.core.data.def.StringCell">
<entry key="StringCell" type="xstring" value="sculpture,lyon,1912,tendresse,marbre,josephbernard,muséedesbeauxartsdelyon"/>
</config>
</config>
<config key="2">
<entry key="datacell" type="xstring" value="org.knime.core.data.def.StringCell"/>
<config key="org.knime.core.data.def.StringCell">
<entry key="StringCell" type="xstring" value="sculpture,lyon,musée,marbre,odalisque,jamespradier,muséedesbeauxartsdelyon"/>
</config>
</config>
<config key="3">
<entry key="datacell" type="xstring" value="org.knime.core.data.def.StringCell"/>
<config key="org.knime.core.data.def.StringCell">
<entry key="StringCell" type="xstring" value="sculpture,lyon,musée,odalisque,jamespradier,muséedesbeauxartsdelyon"/>
</config>
</config>
<config key="4">
<entry key="datacell" type="xstring" value="org.knime.core.data.def.StringCell"/>
<config key="org.knime.core.data.def.StringCell">
<entry key="StringCell" type="xstring" value="square,lofi,squareformat,iphoneography,instagramapp,uploaded:by=instagram,foursquare:venue=4bd4414aa8b3a59350716b5f"/>
</config>
</config>
<config key="5">
<entry key="datacell" type="xstring" value="org.knime.core.data.def.StringCell"/>
<config key="org.knime.core.data.def.StringCell">
<entry key="StringCell" type="xstring" value=""/>
</config>
</config>
<config key="6">
<entry key="datacell" type="xstring" value="org.knime.core.data.def.StringCell"/>
<config key="org.knime.core.data.def.StringCell">
<entry key="StringCell" type="xstring" value="streetart,france,pasteup,collage,paper,europe,lyon,wheatpaste,pasted,croixrousse,agrume,wheatpaper"/>
</config>
</config>
<config key="7">
<entry key="datacell" type="xstring" value="org.knime.core.data.def.StringCell"/>
<config key="org.knime.core.data.def.StringCell">
<entry key="StringCell" type="xstring" value="bear,streetart,france,pasteup,collage,paper,europe,lyon,wheatpaste,pasted,croixrousse,esem,wheatpaper"/>
</config>
</config>
<config key="8">
<entry key="datacell" type="xstring" value="org.knime.core.data.def.StringCell"/>
<config key="org.knime.core.data.def.StringCell">
<entry key="StringCell" type="xstring" value="bw,café,lyon,nb,reflexion,dimanche,ensoleillé"/>
</config>
</config>
<config key="9">
<entry key="datacell" type="xstring" value="org.knime.core.data.def.StringCell"/>
<config key="org.knime.core.data.def.StringCell">
<entry key="StringCell" type="xstring" value="lyon,parcdelatêtedor,héroncendré"/>
</config>
</config>
<config key="10">
<entry key="datacell" type="xstring" value="org.knime.core.data.def.StringCell"/>
<config key="org.knime.core.data.def.StringCell">
<entry key="StringCell" type="xstring" value="lyon,louisxiv,2014,placebellecour,statueéquestre"/>
</config>
</config>
<config key="11">
<entry key="datacell" type="xstring" value="org.knime.core.data.def.StringCell"/>
<config key="org.knime.core.data.def.StringCell">
<entry key="StringCell" type="xstring" value="lyon,uploaded:by=flickrmobile,denimfilter,flickriosapp:filter=denim"/>
</config>
</config>
<config key="12">
<entry key="datacell" type="xstring" value="org.knime.core.data.def.StringCell"/>
<config key="org.knime.core.data.def.StringCell">
<entry key="StringCell" type="xstring" value="lyon,uploaded:by=flickrmobile,flickriosapp:filter=nofilter"/>
</config>
</config>
<config key="13">
<entry key="datacell" type="xstring" value="org.knime.core.data.def.StringCell"/>
<config key="org.knime.core.data.def.StringCell">
<entry key="StringCell" type="xstring" value="lyon,louisxiv,2014,placebellecour,lemot,statueéquestre"/>
</config>
</config>
<config key="14">
<entry key="datacell" type="xstring" value="org.knime.core.data.def.StringCell"/>
<config key="org.knime.core.data.def.StringCell">
<entry key="StringCell" type="xstring" value="lyon,louisxiv,2014,fourvière,placebellecour,lemot,statueéquestre"/>
</config>
</config>
<config key="15">
<entry key="datacell" type="xstring" value="org.knime.core.data.def.StringCell"/>
<config key="org.knime.core.data.def.StringCell">
<entry key="StringCell" type="xstring" value="architecture,lyon,pentax,rhône,moderne,exposition,porte,mur,confluence,immeuble,entrée,justpentax,pentaxart"/>
</config>
</config>
<config key="16">
<entry key="datacell" type="xstring" value="org.knime.core.data.def.StringCell"/>
<config key="org.knime.core.data.def.StringCell">
<entry key="StringCell" type="xstring" value="nude,lyon,femme,gimp,rhône,age,manequin,ville,vitrine,nue,désir,rêve,traitement,rhônealpes,fujix20"/>
</config>
</config>
<config key="17">
<entry key="datacell" type="xstring" value="org.knime.core.data.def.StringCell"/>
<config key="org.knime.core.data.def.StringCell">
<entry key="StringCell" type="xstring" value="world,city,longexposure,bw,france,building,tower,monochrome,architecture,skyscraper,town,blackwhite,europe,lyon,le,leadinglines,rhonealpes,partdieu,rhônealpes,touroxygène"/>
</config>
</config>
<config key="18">
<entry key="datacell" type="xstring" value="org.knime.core.data.def.StringCell"/>
<config key="org.knime.core.data.def.StringCell">
<entry key="StringCell" type="xstring" value="world,city,nightphotography,blue,france,building,tower,night,skyscraper,mall,town,twilight,parkinglot,europe,cityscape,nightscape,lyon,dusk,bluehour,rhonealpes,partdieu,rhônealpes,touroxygène"/>
</config>
</config>
<config key="19">
<entry key="datacell" type="xstring" value="org.knime.core.data.def.StringCell"/>
<config key="org.knime.core.data.def.StringCell">
<entry key="StringCell" type="xstring" value="world,city,longexposure,sunset,people,france,building,church,water,river,town,twilight,europe,cityscape,lyon,dusk,basilica,rhône,le,rhonealpes,hoteldieu,rhônealpes,basiliquedefourvière"/>
</config>
</config>
<config key="20">
<entry key="datacell" type="xstring" value="org.knime.core.data.def.StringCell"/>
<config key="org.knime.core.data.def.StringCell">
<entry key="StringCell" type="xstring" value="lyon,uploaded:by=flickrmobile,throwbackfilter,flickriosapp:filter=throwback"/>
</config>
</config>
<config key="21">
<entry key="datacell" type="xstring" value="org.knime.core.data.def.StringCell"/>
<config key="org.knime.core.data.def.StringCell">
<entry key="StringCell" type="xstring" value="rio,hospital,atardecer,hotel,nikon,lyon,edificio,ciudad,grand,nikkor,puesta,francia,hôtel,1685,rodano,d7000"/>
</config>
</config>
<config key="22">
<entry key="datacell" type="xstring" value="org.knime.core.data.def.StringCell"/>
<config key="org.knime.core.data.def.StringCell">
<entry key="StringCell" type="xstring" value="tower,architecture,lampe,tour,lyon,pentax,rhône,pointe,crayon,fenêtre,immeuble,gratteciel,reverbère,justpentax,pentaxart"/>
</config>
</config>
<config key="23">
<entry key="datacell" type="xstring" value="org.knime.core.data.def.StringCell"/>
<config key="org.knime.core.data.def.StringCell">
<entry key="StringCell" type="xstring" value="park,city,trees,shadow,sky,blackandwhite,white,black,tree,contrast,ink,dark,noir,shadows,natural,lyon,noiretblanc,ombre,ciel,arbres,sombre,contraste,arbre,parc,blanc,ville,encre,ombres,naturel"/>
</config>
</config>
<config key="24">
<entry key="datacell" type="xstring" value="org.knime.core.data.def.StringCell"/>
<config key="org.knime.core.data.def.StringCell">
<entry key="StringCell" type="xstring" value="architecture,lyon,pentax,vert,rhône,moderne,bâtiment,lignes,immeuble,euronews,contemporaine,kaléidoscope,justpentax,pentaxart"/>
</config>
</config>
<config key="25">
<entry key="datacell" type="xstring" value="org.knime.core.data.def.StringCell"/>
<config key="org.knime.core.data.def.StringCell">
<entry key="StringCell" type="xstring" value="canon,lyon,religion,tamron,eglise,colonne,basilique,fourviere,catholique"/>
</config>
</config>
<config key="26">
<entry key="datacell" type="xstring" value="org.knime.core.data.def.StringCell"/>
<config key="org.knime.core.data.def.StringCell">
<entry key="StringCell" type="xstring" value="canon,lyon,tamron,eglise,basilique,fourviere"/>
</config>
</config>
<config key="27">
<entry key="datacell" type="xstring" value="org.knime.core.data.def.StringCell"/>
<config key="org.knime.core.data.def.StringCell">
<entry key="StringCell" type="xstring" value="muscles,tattoo,bmx,body,rhône,skatepark,casquette,tatouage,guillotière,bergesdurhône"/>
</config>
</config>
</config>
</config>
<config key="column_properties"/>
<config key="meta_data"/>
</config>
<config key="column_spec_5">
<entry key="column_name" type="xstring" value="title"/>
<config key="element_names">
<entry key="array-size" type="xint" value="0"/>
</config>
<config key="column_type">
<entry key="cell_class" type="xstring" value="org.knime.core.data.def.StringCell"/>
</config>
<config key="column_domain">
<config key="possible_values">
<entry key="array-size" type="xint" value="55"/>
<config key="0">
<entry key="datacell" type="xstring" value="org.knime.core.data.def.StringCell"/>
<config key="org.knime.core.data.def.StringCell">
<entry key="StringCell" type="xstring" value="Caïn et sa race maudits de Dieu, Antoine Étex, Musée des beaux-arts de Lyon"/>
</config>
</config>
<config key="1">
<entry key="datacell" type="xstring" value="org.knime.core.data.def.StringCell"/>
<config key="org.knime.core.data.def.StringCell">
<entry key="StringCell" type="xstring" value="La Tendresse, Joseph Bernard, Musée des beaux-arts de Lyon"/>
</config>
</config>
<config key="2">
<entry key="datacell" type="xstring" value="org.knime.core.data.def.StringCell"/>
<config key="org.knime.core.data.def.StringCell">
<entry key="StringCell" type="xstring" value="Odalisque de James Pradier, Musée des beaux-arts de Lyon"/>
</config>
</config>
<config key="3">
<entry key="datacell" type="xstring" value="org.knime.core.data.def.StringCell"/>
<config key="org.knime.core.data.def.StringCell">
<entry key="StringCell" type="xstring" value="Musée des beaux-arts de Lyon"/>
</config>
</config>
<config key="4">
<entry key="datacell" type="xstring" value="org.knime.core.data.def.StringCell"/>
<config key="org.knime.core.data.def.StringCell">
<entry key="StringCell" type="xstring" value="10h05"/>
</config>
</config>
<config key="5">
<entry key="datacell" type="xstring" value="org.knime.core.data.def.StringCell"/>
<config key="org.knime.core.data.def.StringCell">
<entry key="StringCell" type="xstring" value="Ce joli nounours et moi nous vous souhaitons une joyeuse Saint Patrick!!!!!!!!!!!"/>
</config>
</config>
<config key="6">
<entry key="datacell" type="xstring" value="org.knime.core.data.def.StringCell"/>
<config key="org.knime.core.data.def.StringCell">
<entry key="StringCell" type="xstring" value="Pasted paper by Agrume  [Lyon, France]"/>
</config>
</config>
<config key="7">
<entry key="datacell" type="xstring" value="org.knime.core.data.def.StringCell"/>
<config key="org.knime.core.data.def.StringCell">
<entry key="StringCell" type="xstring" value="Pasted paper by Esem [Lyon, France]"/>
</config>
</config>
<config key="8">
<entry key="datacell" type="xstring" value="org.knime.core.data.def.StringCell"/>
<config key="org.knime.core.data.def.StringCell">
<entry key="StringCell" type="xstring" value="Dimanche ensoleillé"/>
</config>
</config>
<config key="9">
<entry key="datacell" type="xstring" value="org.knime.core.data.def.StringCell"/>
<config key="org.knime.core.data.def.StringCell">
<entry key="StringCell" type="xstring" value="Parc de la Tête d'Or - Lyon"/>
</config>
</config>
<config key="10">
<entry key="datacell" type="xstring" value="org.knime.core.data.def.StringCell"/>
<config key="org.knime.core.data.def.StringCell">
<entry key="StringCell" type="xstring" value="Statue équestre de Louis XIV, place Bellecour, Lyon"/>
</config>
</config>
<config key="11">
<entry key="datacell" type="xstring" value="org.knime.core.data.def.StringCell"/>
<config key="org.knime.core.data.def.StringCell">
<entry key="StringCell" type="xstring" value="Alstom TGV Duplex n°218  -  SNCF Gare de Lyon Part-Dieu"/>
</config>
</config>
<config key="12">
<entry key="datacell" type="xstring" value="org.knime.core.data.def.StringCell"/>
<config key="org.knime.core.data.def.StringCell">
<entry key="StringCell" type="xstring" value="Alstom TGV Duplex n°203  -  SNCF Gare de Lyon Part-Dieu"/>
</config>
</config>
<config key="13">
<entry key="datacell" type="xstring" value="org.knime.core.data.def.StringCell"/>
<config key="org.knime.core.data.def.StringCell">
<entry key="StringCell" type="xstring" value="Irisbus Citelis 12 n°3123 + 1515  -  Lyon TCL - Lignes C7 et 25"/>
</config>
</config>
<config key="14">
<entry key="datacell" type="xstring" value="org.knime.core.data.def.StringCell"/>
<config key="org.knime.core.data.def.StringCell">
<entry key="StringCell" type="xstring" value="Irisbus Citelis 18 n°2213  -  Lyon TCL - Ligne C25"/>
</config>
</config>
<config key="15">
<entry key="datacell" type="xstring" value="org.knime.core.data.def.StringCell"/>
<config key="org.knime.core.data.def.StringCell">
<entry key="StringCell" type="xstring" value="Irisbus Citelis 12 n°3131  -  Lyon TCL - Ligne C7"/>
</config>
</config>
<config key="16">
<entry key="datacell" type="xstring" value="org.knime.core.data.def.StringCell"/>
<config key="org.knime.core.data.def.StringCell">
<entry key="StringCell" type="xstring" value="Irisbus Citelis 18 n°2812  -  Lyon TCL - Ligne 70"/>
</config>
</config>
<config key="17">
<entry key="datacell" type="xstring" value="org.knime.core.data.def.StringCell"/>
<config key="org.knime.core.data.def.StringCell">
<entry key="StringCell" type="xstring" value="Irisbus Citelis 18 n°2103  -  Lyon TCL - Ligne C12"/>
</config>
</config>
<config key="18">
<entry key="datacell" type="xstring" value="org.knime.core.data.def.StringCell"/>
<config key="org.knime.core.data.def.StringCell">
<entry key="StringCell" type="xstring" value="16 Mars 2014"/>
</config>
</config>
<config key="19">
<entry key="datacell" type="xstring" value="org.knime.core.data.def.StringCell"/>
<config key="org.knime.core.data.def.StringCell">
<entry key="StringCell" type="xstring" value="15 Mars 2014"/>
</config>
</config>
<config key="20">
<entry key="datacell" type="xstring" value="org.knime.core.data.def.StringCell"/>
<config key="org.knime.core.data.def.StringCell">
<entry key="StringCell" type="xstring" value="Sunrise from my hotel room"/>
</config>
</config>
<config key="21">
<entry key="datacell" type="xstring" value="org.knime.core.data.def.StringCell"/>
<config key="org.knime.core.data.def.StringCell">
<entry key="StringCell" type="xstring" value="art in my hotel room"/>
</config>
</config>
<config key="22">
<entry key="datacell" type="xstring" value="org.knime.core.data.def.StringCell"/>
<config key="org.knime.core.data.def.StringCell">
<entry key="StringCell" type="xstring" value="Sun Rise from my hotel room"/>
</config>
</config>
<config key="23">
<entry key="datacell" type="xstring" value="org.knime.core.data.def.StringCell"/>
<config key="org.knime.core.data.def.StringCell">
<entry key="StringCell" type="xstring" value="downtown Lyon France"/>
</config>
</config>
<config key="24">
<entry key="datacell" type="xstring" value="org.knime.core.data.def.StringCell"/>
<config key="org.knime.core.data.def.StringCell">
<entry key="StringCell" type="xstring" value="La fille en rouge sur sa Balançoire"/>
</config>
</config>
<config key="25">
<entry key="datacell" type="xstring" value="org.knime.core.data.def.StringCell"/>
<config key="org.knime.core.data.def.StringCell">
<entry key="StringCell" type="xstring" value="Alstom TGV Sud-Est n°25 + Duplex n°271  -  Gare SNCF Lyon Part-Dieu"/>
</config>
</config>
<config key="26">
<entry key="datacell" type="xstring" value="org.knime.core.data.def.StringCell"/>
<config key="org.knime.core.data.def.StringCell">
<entry key="StringCell" type="xstring" value="Alstom TGV Sud-Est n°25 + 18 et Z26500  -  SNCF Gare de Lyon Part-Dieu"/>
</config>
</config>
<config key="27">
<entry key="datacell" type="xstring" value="org.knime.core.data.def.StringCell"/>
<config key="org.knime.core.data.def.StringCell">
<entry key="StringCell" type="xstring" value="Entrée libre"/>
</config>
</config>
<config key="28">
<entry key="datacell" type="xstring" value="org.knime.core.data.def.StringCell"/>
<config key="org.knime.core.data.def.StringCell">
<entry key="StringCell" type="xstring" value="j'ai parfois ce rêve étrange et envoûtant... I sometimes have this strange and spellbinding a dream..."/>
</config>
</config>
<config key="29">
<entry key="datacell" type="xstring" value="org.knime.core.data.def.StringCell"/>
<config key="org.knime.core.data.def.StringCell">
<entry key="StringCell" type="xstring" value="On the edge of darkness"/>
</config>
</config>
<config key="30">
<entry key="datacell" type="xstring" value="org.knime.core.data.def.StringCell"/>
<config key="org.knime.core.data.def.StringCell">
<entry key="StringCell" type="xstring" value="Peaceful evening"/>
</config>
</config>
<config key="31">
<entry key="datacell" type="xstring" value="org.knime.core.data.def.StringCell"/>
<config key="org.knime.core.data.def.StringCell">
<entry key="StringCell" type="xstring" value="What A Perfect Evening She Said"/>
</config>
</config>
<config key="32">
<entry key="datacell" type="xstring" value="org.knime.core.data.def.StringCell"/>
<config key="org.knime.core.data.def.StringCell">
<entry key="StringCell" type="xstring" value="14 Mars 2014"/>
</config>
</config>
<config key="33">
<entry key="datacell" type="xstring" value="org.knime.core.data.def.StringCell"/>
<config key="org.knime.core.data.def.StringCell">
<entry key="StringCell" type="xstring" value="Le Grand Hôtel-Dieu"/>
</config>
</config>
<config key="34">
<entry key="datacell" type="xstring" value="org.knime.core.data.def.StringCell"/>
<config key="org.knime.core.data.def.StringCell">
<entry key="StringCell" type="xstring" value="Le crayon"/>
</config>
</config>
<config key="35">
<entry key="datacell" type="xstring" value="org.knime.core.data.def.StringCell"/>
<config key="org.knime.core.data.def.StringCell">
<entry key="StringCell" type="xstring" value="Parc tête d'Or automne_19"/>
</config>
</config>
<config key="36">
<entry key="datacell" type="xstring" value="org.knime.core.data.def.StringCell"/>
<config key="org.knime.core.data.def.StringCell">
<entry key="StringCell" type="xstring" value="Sans titre"/>
</config>
</config>
<config key="37">
<entry key="datacell" type="xstring" value="org.knime.core.data.def.StringCell"/>
<config key="org.knime.core.data.def.StringCell">
<entry key="StringCell" type="xstring" value="Fourvière"/>
</config>
</config>
<config key="38">
<entry key="datacell" type="xstring" value="org.knime.core.data.def.StringCell"/>
<config key="org.knime.core.data.def.StringCell">
<entry key="StringCell" type="xstring" value="Body"/>
</config>
</config>
<config key="39">
<entry key="datacell" type="xstring" value="org.knime.core.data.def.StringCell"/>
<config key="org.knime.core.data.def.StringCell">
<entry key="StringCell" type="xstring" value="Alstom Citadis 302 n°854  -  Lyon TCL - Ligne T2"/>
</config>
</config>
<config key="40">
<entry key="datacell" type="xstring" value="org.knime.core.data.def.StringCell"/>
<config key="org.knime.core.data.def.StringCell">
<entry key="StringCell" type="xstring" value="Alstom MPL 75  -  Lyon TCL - Ligne A"/>
</config>
</config>
<config key="41">
<entry key="datacell" type="xstring" value="org.knime.core.data.def.StringCell"/>
<config key="org.knime.core.data.def.StringCell">
<entry key="StringCell" type="xstring" value="Station Croix-Paquet  -  Lyon TCL - Ligne C"/>
</config>
</config>
<config key="42">
<entry key="datacell" type="xstring" value="org.knime.core.data.def.StringCell"/>
<config key="org.knime.core.data.def.StringCell">
<entry key="StringCell" type="xstring" value="Alstom MCL 80 n°203/4  -  Lyon TCL - Ligne C"/>
</config>
</config>
<config key="43">
<entry key="datacell" type="xstring" value="org.knime.core.data.def.StringCell"/>
<config key="org.knime.core.data.def.StringCell">
<entry key="StringCell" type="xstring" value="Station Croix Paquet  -  Lyon TCL - Ligne C"/>
</config>
</config>
<config key="44">
<entry key="datacell" type="xstring" value="org.knime.core.data.def.StringCell"/>
<config key="org.knime.core.data.def.StringCell">
<entry key="StringCell" type="xstring" value="Alstom MCL 80 n°207/8  -  Lyon TCL - Ligne C"/>
</config>
</config>
<config key="45">
<entry key="datacell" type="xstring" value="org.knime.core.data.def.StringCell"/>
<config key="org.knime.core.data.def.StringCell">
<entry key="StringCell" type="xstring" value="Alstom Citadis 302 n°847  -  Lyon TCL - Ligne T1"/>
</config>
</config>
<config key="46">
<entry key="datacell" type="xstring" value="org.knime.core.data.def.StringCell"/>
<config key="org.knime.core.data.def.StringCell">
<entry key="StringCell" type="xstring" value="Alstom Citadis 302 n°840  -  Lyon TCL - Ligne T1"/>
</config>
</config>
<config key="47">
<entry key="datacell" type="xstring" value="org.knime.core.data.def.StringCell"/>
<config key="org.knime.core.data.def.StringCell">
<entry key="StringCell" type="xstring" value="Alstom Citadis 302 n°846  -  Lyon TCL - Ligne T1"/>
</config>
</config>
<config key="48">
<entry key="datacell" type="xstring" value="org.knime.core.data.def.StringCell"/>
<config key="org.knime.core.data.def.StringCell">
<entry key="StringCell" type="xstring" value="Pont Raymond Barre  -  Lyon"/>
</config>
</config>
<config key="49">
<entry key="datacell" type="xstring" value="org.knime.core.data.def.StringCell"/>
<config key="org.knime.core.data.def.StringCell">
<entry key="StringCell" type="xstring" value="Alstom Citadis 302 n°830  -  Lyon TCL - Ligne T1"/>
</config>
</config>
<config key="50">
<entry key="datacell" type="xstring" value="org.knime.core.data.def.StringCell"/>
<config key="org.knime.core.data.def.StringCell">
<entry key="StringCell" type="xstring" value="Ecrans d'infos voyageurs Citadis 302  -  Lyon TCL"/>
</config>
</config>
<config key="51">
<entry key="datacell" type="xstring" value="org.knime.core.data.def.StringCell"/>
<config key="org.knime.core.data.def.StringCell">
<entry key="StringCell" type="xstring" value="Basilica of Notre-Dame de Fourvière"/>
</config>
</config>
<config key="52">
<entry key="datacell" type="xstring" value="org.knime.core.data.def.StringCell"/>
<config key="org.knime.core.data.def.StringCell">
<entry key="StringCell" type="xstring" value="Old Town Lyon"/>
</config>
</config>
<config key="53">
<entry key="datacell" type="xstring" value="org.knime.core.data.def.StringCell"/>
<config key="org.knime.core.data.def.StringCell">
<entry key="StringCell" type="xstring" value="Saint-Jean-Baptiste Cathedral, Place Saint-Jean, 69005, Lyon, France"/>
</config>
</config>
<config key="54">
<entry key="datacell" type="xstring" value="org.knime.core.data.def.StringCell"/>
<config key="org.knime.core.data.def.StringCell">
<entry key="StringCell" type="xstring" value="Palais de Justice, Lyon France"/>
</config>
</config>
</config>
</config>
<config key="column_properties"/>
<config key="meta_data"/>
</config>
<config key="column_spec_6">
<entry key="column_name" type="xstring" value="date_taken_minute"/>
<config key="element_names">
<entry key="array-size" type="xint" value="0"/>
</config>
<config key="column_type">
<entry key="cell_class" type="xstring" value="org.knime.core.data.def.IntCell"/>
</config>
<config key="column_domain">
<config key="lower_bound">
<entry key="datacell" type="xstring" value="org.knime.core.data.def.IntCell"/>
<config key="org.knime.core.data.def.IntCell">
<entry key="IntCell" type="xint" value="0"/>
</config>
</config>
<config key="upper_bound">
<entry key="datacell" type="xstring" value="org.knime.core.data.def.IntCell"/>
<config key="org.knime.core.data.def.IntCell">
<entry key="IntCell" type="xint" value="59"/>
</config>
</config>
</config>
<config key="column_properties"/>
<config key="meta_data"/>
</config>
<config key="column_spec_7">
<entry key="column_name" type="xstring" value="date_taken_hour"/>
<config key="element_names">
<entry key="array-size" type="xint" value="0"/>
</config>
<config key="column_type">
<entry key="cell_class" type="xstring" value="org.knime.core.data.def.IntCell"/>
</config>
<config key="column_domain">
<config key="lower_bound">
<entry key="datacell" type="xstring" value="org.knime.core.data.def.IntCell"/>
<config key="org.knime.core.data.def.IntCell">
<entry key="IntCell" type="xint" value="0"/>
</config>
</config>
<config key="upper_bound">
<entry key="datacell" type="xstring" value="org.knime.core.data.def.IntCell"/>
<config key="org.knime.core.data.def.IntCell">
<entry key="IntCell" type="xint" value="23"/>
</config>
</config>
</config>
<config key="column_properties"/>
<config key="meta_data"/>
</config>
<config key="column_spec_8">
<entry key="column_name" type="xstring" value="date_taken_day"/>
<config key="element_names">
<entry key="array-size" type="xint" value="0"/>
</config>
<config key="column_type">
<entry key="cell_class" type="xstring" value="org.knime.core.data.def.IntCell"/>
</config>
<config key="column_domain">
<config key="lower_bound">
<entry key="datacell" type="xstring" value="org.knime.core.data.def.IntCell"/>
<config key="org.knime.core.data.def.IntCell">
<entry key="IntCell" type="xint" value="1"/>
</config>
</config>
<config key="upper_bound">
<entry key="datacell" type="xstring" value="org.knime.core.data.def.IntCell"/>
<config key="org.knime.core.data.def.IntCell">
<entry key="IntCell" type="xint" value="31"/>
</config>
</config>
</config>
<config key="column_properties"/>
<config key="meta_data"/>
</config>
<config key="column_spec_9">
<entry key="column_name" type="xstring" value="date_taken_month"/>
<config key="element_names">
<entry key="array-size" type="xint" value="0"/>
</config>
<config key="column_type">
<entry key="cell_class" type="xstring" value="org.knime.core.data.def.IntCell"/>
</config>
<config key="column_domain">
<config key="lower_bound">
<entry key="datacell" type="xstring" value="org.knime.core.data.def.IntCell"/>
<config key="org.knime.core.data.def.IntCell">
<entry key="IntCell" type="xint" value="1"/>
</config>
</config>
<config key="upper_bound">
<entry key="datacell" type="xstring" value="org.knime.core.data.def.IntCell"/>
<config key="org.knime.core.data.def.IntCell">
<entry key="IntCell" type="xint" value="12"/>
</config>
</config>
</config>
<config key="column_properties"/>
<config key="meta_data"/>
</config>
<config key="column_spec_10">
<entry key="column_name" type="xstring" value="date_taken_year"/>
<config key="element_names">
<entry key="array-size" type="xint" value="0"/>
</config>
<config key="column_type">
<entry key="cell_class" type="xstring" value="org.knime.core.data.def.IntCell"/>
</config>
<config key="column_domain">
<config key="lower_bound">
<entry key="datacell" type="xstring" value="org.knime.core.data.def.IntCell"/>
<config key="org.knime.core.data.def.IntCell">
<entry key="IntCell" type="xint" value="1957"/>
</config>
</config>
<config key="upper_bound">
<entry key="datacell" type="xstring" value="org.knime.core.data.def.IntCell"/>
<config key="org.knime.core.data.def.IntCell">
<entry key="IntCell" type="xint" value="2015"/>
</config>
</config>
</config>
<config key="column_properties"/>
<config key="meta_data"/>
</config>
<config key="column_spec_11">
<entry key="column_name" type="xstring" value="date_upload_minute"/>
<config key="element_names">
<entry key="array-size" type="xint" value="0"/>
</config>
<config key="column_type">
<entry key="cell_class" type="xstring" value="org.knime.core.data.def.IntCell"/>
</config>
<config key="column_domain">
<config key="lower_bound">
<entry key="datacell" type="xstring" value="org.knime.core.data.def.IntCell"/>
<config key="org.knime.core.data.def.IntCell">
<entry key="IntCell" type="xint" value="0"/>
</config>
</config>
<config key="upper_bound">
<entry key="datacell" type="xstring" value="org.knime.core.data.def.IntCell"/>
<config key="org.knime.core.data.def.IntCell">
<entry key="IntCell" type="xint" value="59"/>
</config>
</config>
</config>
<config key="column_properties"/>
<config key="meta_data"/>
</config>
<config key="column_spec_12">
<entry key="column_name" type="xstring" value="date_upload_hour"/>
<config key="element_names">
<entry key="array-size" type="xint" value="0"/>
</config>
<config key="column_type">
<entry key="cell_class" type="xstring" value="org.knime.core.data.def.IntCell"/>
</config>
<config key="column_domain">
<config key="lower_bound">
<entry key="datacell" type="xstring" value="org.knime.core.data.def.IntCell"/>
<config key="org.knime.core.data.def.IntCell">
<entry key="IntCell" type="xint" value="0"/>
</config>
</config>
<config key="upper_bound">
<entry key="datacell" type="xstring" value="org.knime.core.data.def.IntCell"/>
<config key="org.knime.core.data.def.IntCell">
<entry key="IntCell" type="xint" value="23"/>
</config>
</config>
</config>
<config key="column_properties"/>
<config key="meta_data"/>
</config>
<config key="column_spec_13">
<entry key="column_name" type="xstring" value="date_upload_day"/>
<config key="element_names">
<entry key="array-size" type="xint" value="0"/>
</config>
<config key="column_type">
<entry key="cell_class" type="xstring" value="org.knime.core.data.def.IntCell"/>
</config>
<config key="column_domain">
<config key="lower_bound">
<entry key="datacell" type="xstring" value="org.knime.core.data.def.IntCell"/>
<config key="org.knime.core.data.def.IntCell">
<entry key="IntCell" type="xint" value="1"/>
</config>
</config>
<config key="upper_bound">
<entry key="datacell" type="xstring" value="org.knime.core.data.def.IntCell"/>
<config key="org.knime.core.data.def.IntCell">
<entry key="IntCell" type="xint" value="31"/>
</config>
</config>
</config>
<config key="column_properties"/>
<config key="meta_data"/>
</config>
<config key="column_spec_14">
<entry key="column_name" type="xstring" value="date_upload_month"/>
<config key="element_names">
<entry key="array-size" type="xint" value="0"/>
</config>
<config key="column_type">
<entry key="cell_class" type="xstring" value="org.knime.core.data.def.IntCell"/>
</config>
<config key="column_domain">
<config key="lower_bound">
<entry key="datacell" type="xstring" value="org.knime.core.data.def.IntCell"/>
<config key="org.knime.core.data.def.IntCell">
<entry key="IntCell" type="xint" value="1"/>
</config>
</config>
<config key="upper_bound">
<entry key="datacell" type="xstring" value="org.knime.core.data.def.IntCell"/>
<config key="org.knime.core.data.def.IntCell">
<entry key="IntCell" type="xint" value="11"/>
</config>
</config>
</config>
<config key="column_properties"/>
<config key="meta_data"/>
</config>
<config key="column_spec_15">
<entry key="column_name" type="xstring" value="date_upload_year"/>
<config key="element_names">
<entry key="array-size" type="xint" value="0"/>
</config>
<config key="column_type">
<entry key="cell_class" type="xstring" value="org.knime.core.data.def.IntCell"/>
</config>
<config key="column_domain">
<config key="lower_bound">
<entry key="datacell" type="xstring" value="org.knime.core.data.def.IntCell"/>
<config key="org.knime.core.data.def.IntCell">
<entry key="IntCell" type="xint" value="2014"/>
</config>
</config>
<config key="upper_bound">
<entry key="datacell" type="xstring" value="org.knime.core.data.def.IntCell"/>
<config key="org.knime.core.data.def.IntCell">
<entry key="IntCell" type="xint" value="2015"/>
</config>
</config>
</config>
<config key="column_properties"/>
<config key="meta_data"/>
</config>
</config>
